tests
py_razor_client
