Metadata-Version: 1.1
Name: py-razor-client
Version: 0.1.2
Summary: A simple Python library for interacting with Razor
Home-page: https://github.com/fhats/py_razor_client
Author: Fred Hatfull
Author-email: fred.hatfull@gmail.com
License: MIT
Keywords: razor razor-server imaging library
Platform: UNKNOWN
Classifier: Development Status :: 3 - Alpha
Classifier: Topic :: Utilities
Classifier: License :: OSI Approved :: MIT License
Classifier: Topic :: Software Development :: Libraries
Classifier: Topic :: Software Development :: Libraries :: Python Modules
Classifier: Topic :: System :: Systems Administration
Classifier: Topic :: System :: Installation/Setup
